{
  "accuracy": 1.0,
  "branch_count": 25,
  "dataset": "chscase_census3.txt",
  "dataset_path": "data/openml/sampled/chscase_census3.txt",
  "error": null,
  "expansions": 51736,
  "memory_usage_bytes": 4295046179,
  "n_examples": 100,
  "n_features": 7,
  "runtime_seconds": 889.3526028850029,
  "solved": true,
  "solver": "codt",
  "status": "perfect-tree-found",
  "tree": "[3, 4.156750000000001, [2, 4.15555, [2, 4.114000000000001, 0, 1], [2, 4.3057, 0, [2, 4.3067, 1, 0]]], [0, 3.88895, 0, [3, 4.2165, [1, 4.2139500000000005, [6, 4.1998999999999995, 0, [4, 4.210100000000001, 1, [5, 4.22535, 1, [5, 4.25725, 0, 1]]]], 1], [2, 4.31005, [0, 4.22375, [1, 4.2071000000000005, [4, 4.2202, 0, 1], 1], [4, 4.2057, 0, [2, 4.2592, [4, 4.2503, [2, 4.1762, 1, 0], [3, 4.2661, 0, [6, 4.24655, [4, 4.2951, 0, 1], 1]]], 1]]], [4, 4.311999999999999, [5, 4.31745, 0, 1], 1]]]]]",
  "tree_size": 51
}